visionVault/App.py
visionVault/Sift_keypoints.py
visionVault/TEST.py
visionVault/__init__.py
visionVault/delete.py
visionVault/features.py
visionVault/readrr.py
visionVault/symmetry.py
visionVault/transformation.py
visionVault-0.1.0.dist-info/METADATA
visionVault-0.1.0.dist-info/WHEEL
visionVault-0.1.0.dist-info/top_level.txt
visionVault-0.1.0.dist-info/RECORD
