Metadata-Version: 2.1
Name: visionVault
Version: 0.1.0
Summary: Image profiling library
Author: @itertools
Requires-Dist: requirements.txt
